{"duration":247,"records":[{"duration":80,"stepId":"io.quarkus.deployment.ide.IdeProcessor#detectRunningIdeProcesses","started":"16:12:07.772","dependents":[241],"id":240,"thread":"build-4"},{"duration":69,"stepId":"io.quarkus.deployment.steps.MainClassBuildStep#build","started":"16:12:07.948","dependents":[],"id":310,"thread":"build-35"},{"duration":54,"stepId":"io.quarkus.vertx.http.deployment.webjar.WebJarProcessor#processWebJarDevMode","started":"16:12:07.788","dependents":[288,310,237],"id":236,"thread":"build-16"},{"duration":38,"stepId":"io.quarkus.qute.deployment.QuteProcessor#collectTemplates","started":"16:12:07.795","dependents":[265,230,259,226,267,266,227,231,228,280],"id":224,"thread":"build-19"},{"duration":36,"stepId":"io.quarkus.arc.deployment.ArcProcessor#generateResources","started":"16:12:07.889","dependents":[309,290,310,293],"id":289,"thread":"build-16"},{"duration":34,"stepId":"io.quarkus.arc.deployment.BeanArchiveProcessor#build","started":"16:12:07.797","dependents":[255,257,261,230,233,218,232,216,262,215,217,263,219,223,220,256,229,266,238,225],"id":214,"thread":"build-6"},{"duration":22,"stepId":"io.quarkus.deployment.steps.ConfigDescriptionBuildStep#createConfigDescriptions","started":"16:12:07.774","dependents":[203,305],"id":186,"thread":"build-1"},{"duration":18,"stepId":"io.quarkus.vertx.http.deployment.devmode.console.DevConsoleProcessor#setupDeploymentSideHandling","started":"16:12:07.929","dependents":[307,306],"id":305,"thread":"build-35"},{"duration":14,"stepId":"io.quarkus.arc.deployment.ArcProcessor#registerBeans","started":"16:12:07.843","dependents":[255,257,271,261,246,270,247,269,263,268,248,251,256,249,250,252],"id":245,"thread":"build-20"},{"duration":14,"stepId":"io.quarkus.qute.deployment.QuteProcessor#generateValueResolvers","started":"16:12:07.862","dependents":[309,267],"id":266,"thread":"build-12"},{"duration":12,"stepId":"io.quarkus.vertx.http.deployment.StaticResourcesProcessor#collectStaticResources","started":"16:12:07.795","dependents":[295],"id":213,"thread":"build-15"},{"duration":10,"stepId":"io.quarkus.deployment.dev.HotDeploymentWatchedFileBuildStep#setupWatchedFileHotDeployment","started":"16:12:07.859","dependents":[307,306],"id":265,"thread":"build-29"},{"duration":10,"stepId":"io.quarkus.resteasy.deployment.ResteasyBuiltinsProcessor#addStaticResourcesExceptionMapper","started":"16:12:07.796","dependents":[310],"id":212,"thread":"build-22"},{"duration":7,"stepId":"io.quarkus.resteasy.common.deployment.ResteasyCommonProcessor#setupProviders","started":"16:12:07.833","dependents":[273,233,309,279],"id":232,"thread":"build-22"},{"duration":7,"stepId":"io.quarkus.deployment.steps.BannerProcessor#recordBanner","started":"16:12:07.792","dependents":[253,310],"id":195,"thread":"build-20"},{"duration":6,"stepId":"io.quarkus.deployment.steps.ApplicationIndexBuildStep#build","started":"16:12:07.786","dependents":[165,238,252,167],"id":161,"thread":"build-15"},{"duration":6,"stepId":"io.quarkus.vertx.http.deployment.devmode.console.DevConsoleProcessor#collectTemplates","started":"16:12:07.781","dependents":[305],"id":136,"thread":"build-9"},{"duration":5,"stepId":"io.quarkus.vertx.http.deployment.devmode.console.ConfigEditorProcessor#config","started":"16:12:07.797","dependents":[288,305,204,306,310],"id":203,"thread":"build-3"},{"duration":5,"stepId":"io.quarkus.deployment.steps.ThreadPoolSetup#createExecutor","started":"16:12:07.794","dependents":[202,303,198,197,299,205,310],"id":196,"thread":"build-27"},{"duration":5,"stepId":"io.quarkus.arc.deployment.ArcProcessor#validate","started":"16:12:07.881","dependents":[275,274,276,285,286,289,277,280,293,278,279],"id":273,"thread":"build-31"},{"duration":4,"stepId":"io.quarkus.deployment.logging.LoggingResourceProcessor#setupLoggingRuntimeInit","started":"16:12:07.854","dependents":[288,309,305,304,310],"id":253,"thread":"build-31"},{"duration":4,"stepId":"io.quarkus.vertx.http.deployment.devmode.ArcDevProcessor#invocationsEndpoint","started":"16:12:07.773","dependents":[288,305,310],"id":78,"thread":"build-3"},{"duration":4,"stepId":"io.quarkus.deployment.steps.ConfigGenerationBuildStep#checkForBuildTimeConfigChange","started":"16:12:07.793","dependents":[310],"id":181,"thread":"build-17"},{"duration":3,"stepId":"io.quarkus.vertx.core.deployment.VertxCoreProcessor#build_9fb3ce360263cc99d07c9172ec2feeaa85afcc1a","started":"16:12:07.800","dependents":[254,206,270,307,306,269,268,303,295,299,308,302,209,310],"id":205,"thread":"build-14"},{"duration":3,"stepId":"io.quarkus.vertx.http.deployment.devmode.console.DevConsoleProcessor#setupDevConsoleRoutes_0a9629c46f632dba90d4b3c7602ae4ea9d736452","started":"16:12:07.891","dependents":[305,300,302,310],"id":288,"thread":"build-28"},{"duration":3,"stepId":"io.quarkus.smallrye.context.deployment.SmallRyeContextPropagationProcessor#build","started":"16:12:07.800","dependents":[268,270,269,310],"id":202,"thread":"build-20"},{"duration":3,"stepId":"io.quarkus.arc.deployment.devconsole.ArcDevConsoleProcessor#collectBeanInfo","started":"16:12:07.887","dependents":[288,305,287],"id":286,"thread":"build-32"},{"duration":2,"stepId":"io.quarkus.smallrye.context.deployment.SmallRyeContextPropagationProcessor#buildStatic","started":"16:12:07.784","dependents":[310],"id":132,"thread":"build-7"},{"duration":2,"stepId":"io.quarkus.deployment.steps.ClassTransformingBuildStep#handleClassTransformation","started":"16:12:07.924","dependents":[],"id":293,"thread":"build-35"},{"duration":2,"stepId":"io.quarkus.vertx.http.deployment.devmode.ArcDevProcessor#eventsEndpoint","started":"16:12:07.775","dependents":[288,305,310],"id":77,"thread":"build-9"},{"duration":2,"stepId":"io.quarkus.qute.deployment.MessageBundleProcessor#processBundles","started":"16:12:07.857","dependents":[265,271,259,258,260,263],"id":255,"thread":"build-22"},{"duration":2,"stepId":"io.quarkus.arc.deployment.SyntheticBeansProcessor#initRuntime","started":"16:12:07.877","dependents":[271,307,306,310],"id":270,"thread":"build-22"},{"duration":2,"stepId":"io.quarkus.arc.deployment.staticmethods.InterceptedStaticMethodsProcessor#collectInterceptedStaticMethods","started":"16:12:07.857","dependents":[273,257,291,279],"id":256,"thread":"build-14"},{"duration":2,"stepId":"io.quarkus.vertx.http.deployment.StaticResourcesProcessor#runtimeInit","started":"16:12:07.924","dependents":[303,310],"id":295,"thread":"build-15"},{"duration":2,"stepId":"io.quarkus.resteasy.common.deployment.ResteasyCommonProcessor#setupResteasyInjection","started":"16:12:07.924","dependents":[298,296,310],"id":294,"thread":"build-26"},{"duration":1,"stepId":"io.quarkus.deployment.steps.ConfigGenerationBuildStep#buildTimeRunTimeConfig","started":"16:12:07.782","dependents":[284,309],"id":128,"thread":"build-10"},{"duration":1,"stepId":"io.quarkus.vertx.http.deployment.HttpSecurityProcessor#initBasicAuth","started":"16:12:07.793","dependents":[268,270,269,310],"id":166,"thread":"build-21"},{"duration":1,"stepId":"io.quarkus.resteasy.deployment.ResteasyStandaloneBuildStep#addDefaultAuthFailureHandler","started":"16:12:07.783","dependents":[303,310],"id":129,"thread":"build-15"},{"duration":1,"stepId":"io.quarkus.vertx.http.deployment.devmode.tests.TestsProcessor#setupTestRoutes","started":"16:12:07.779","dependents":[305,300,152,302,310],"id":112,"thread":"build-10"},{"duration":1,"stepId":"io.quarkus.vertx.http.deployment.VertxHttpProcessor#preinitializeRouter","started":"16:12:07.804","dependents":[268,270,302,269,310],"id":209,"thread":"build-3"},{"duration":1,"stepId":"io.quarkus.vertx.http.deployment.devmode.ArcDevProcessor#registerRoutes","started":"16:12:07.887","dependents":[301,289,305,300,302,310],"id":285,"thread":"build-14"},{"duration":1,"stepId":"io.quarkus.deployment.steps.ConfigGenerationBuildStep#watchConfigFiles","started":"16:12:07.774","dependents":[265],"id":64,"thread":"build-2"},{"duration":1,"stepId":"io.quarkus.deployment.ide.IdeProcessor#detectIdeFiles","started":"16:12:07.778","dependents":[241],"id":111,"thread":"build-2"},{"duration":1,"stepId":"io.quarkus.resteasy.server.common.deployment.ResteasyServerCommonProcessor#build","started":"16:12:07.840","dependents":[273,309,238,239,298,234,296,293,279],"id":233,"thread":"build-20"},{"duration":1,"stepId":"io.quarkus.resteasy.deployment.ResteasyStandaloneBuildStep#boot","started":"16:12:07.928","dependents":[303,305,300,302,310],"id":299,"thread":"build-26"},{"duration":1,"stepId":"io.quarkus.qute.deployment.QuteProcessor#analyzeTemplates","started":"16:12:07.859","dependents":[261,264,266,262,260,263],"id":259,"thread":"build-31"},{"duration":1,"stepId":"io.quarkus.deployment.steps.ReflectiveHierarchyStep#build","started":"16:12:07.842","dependents":[309],"id":239,"thread":"build-22"},{"duration":1,"stepId":"io.quarkus.vertx.http.deployment.VertxHttpProcessor#finalizeRouter","started":"16:12:07.930","dependents":[304,307,306,310],"id":303,"thread":"build-26"},{"duration":1,"stepId":"io.quarkus.vertx.core.deployment.VertxCoreProcessor#createVertxThreadFactory","started":"16:12:07.775","dependents":[196,310],"id":76,"thread":"build-2"},{"duration":1,"stepId":"io.quarkus.arc.deployment.SplitPackageProcessor#splitPackageDetection","started":"16:12:07.796","dependents":[289],"id":185,"thread":"build-9"},{"duration":1,"stepId":"io.quarkus.deployment.steps.DevServicesConfigBuildStep#setup","started":"16:12:07.772","dependents":[203,283,307,45,306],"id":42,"thread":"build-7"},{"duration":1,"stepId":"io.quarkus.deployment.index.ApplicationArchiveBuildStep#build","started":"16:12:07.793","dependents":[255,244,224,212,169,293,213,214,171,178,185,266,298,277],"id":165,"thread":"build-23"},{"duration":1,"stepId":"io.quarkus.qute.deployment.QuteProcessor#initialize","started":"16:12:07.876","dependents":[268,270,269,310],"id":267,"thread":"build-29"},{"duration":1,"stepId":"io.quarkus.qute.deployment.MessageBundleProcessor#initBundleContext","started":"16:12:07.859","dependents":[268,270,269,310],"id":258,"thread":"build-12"},{"duration":1,"stepId":"io.quarkus.vertx.http.deployment.VertxHttpProcessor#cors","started":"16:12:07.792","dependents":[303,310],"id":163,"thread":"build-22"},{"duration":1,"stepId":"io.quarkus.vertx.deployment.VertxProcessor#currentContextFactory","started":"16:12:07.791","dependents":[289,310],"id":160,"thread":"build-23"},{"duration":1,"stepId":"io.quarkus.vertx.core.deployment.VertxCoreProcessor#eventLoopCount","started":"16:12:07.792","dependents":[308,310],"id":164,"thread":"build-19"},{"duration":1,"stepId":"io.quarkus.vertx.deployment.VertxProcessor#build","started":"16:12:07.857","dependents":[309,307,306,310],"id":254,"thread":"build-29"},{"duration":1,"stepId":"io.quarkus.deployment.logging.LoggingResourceProcessor#logConsoleCommand","started":"16:12:07.789","dependents":[204],"id":154,"thread":"build-18"},{"duration":1,"stepId":"io.quarkus.arc.deployment.ArcProcessor#initialize","started":"16:12:07.842","dependents":[286,245],"id":238,"thread":"build-31"},{"duration":1,"stepId":"io.quarkus.vertx.http.deployment.VertxHttpProcessor#bodyHandler","started":"16:12:07.793","dependents":[303,288,310],"id":168,"thread":"build-2"},{"duration":1,"stepId":"io.quarkus.vertx.core.deployment.VertxCoreProcessor#createVertxContextHandlers","started":"16:12:07.780","dependents":[197,196,310],"id":121,"thread":"build-2"},{"duration":1,"stepId":"io.quarkus.vertx.core.deployment.VertxCoreProcessor#ioThreadDetector","started":"16:12:07.779","dependents":[207,310],"id":109,"thread":"build-9"},{"duration":1,"stepId":"io.quarkus.deployment.dev.testing.TestTracingProcessor#testConsoleCommand","started":"16:12:07.797","dependents":[204],"id":194,"thread":"build-11"},{"duration":1,"stepId":"io.quarkus.vertx.http.deployment.VertxHttpProcessor#initializeRouter","started":"16:12:07.929","dependents":[303,310],"id":302,"thread":"build-36"},{"duration":1,"stepId":"io.quarkus.vertx.http.deployment.devmode.console.DevConsoleProcessor#handler","started":"16:12:07.778","dependents":[288,253,310],"id":106,"thread":"build-7"},{"duration":0,"stepId":"io.quarkus.qute.deployment.QuteProcessor#turnLocationIntoQualifier","started":"16:12:07.788","dependents":[218,238],"id":141,"thread":"build-16"},{"duration":0,"stepId":"io.quarkus.vertx.http.deployment.devmode.console.DevConsoleProcessor#builder","started":"16:12:07.852","dependents":[288,305],"id":243,"thread":"build-4"},{"duration":0,"stepId":"io.quarkus.vertx.http.deployment.devmode.console.DevConsoleProcessor#setupConsole","started":"16:12:07.781","dependents":[307,306],"id":120,"thread":"build-10"},{"duration":0,"stepId":"io.quarkus.arc.deployment.BuildTimeEnabledProcessor#unlessBuildProperty","started":"16:12:07.797","dependents":[192,233],"id":187,"thread":"build-9"},{"duration":0,"stepId":"io.quarkus.vertx.deployment.VertxProcessor#registerVerticleClasses","started":"16:12:07.797","dependents":[309],"id":183,"thread":"build-6"},{"duration":0,"stepId":"io.quarkus.deployment.steps.ReflectiveHierarchyStep#ignoreJavaClassWarnings","started":"16:12:07.772","dependents":[239],"id":23,"thread":"build-9"},{"duration":0,"stepId":"io.quarkus.deployment.steps.ConfigGenerationBuildStep#suppressNonRuntimeConfigChanged","started":"16:12:07.772","dependents":[181],"id":18,"thread":"build-5"},{"duration":0,"stepId":"io.quarkus.vertx.http.deployment.devmode.tests.TestsProcessor#toggleTestRunner","started":"16:12:07.774","dependents":[288,305],"id":54,"thread":"build-9"},{"duration":0,"stepId":"io.quarkus.resteasy.jsonb.deployment.ResteasyJsonbProcessor#registerVertxJsonSupport","started":"16:12:07.773","dependents":[43],"id":34,"thread":"build-5"},{"duration":0,"stepId":"io.quarkus.deployment.steps.ConfigGenerationBuildStep#staticInitSources","started":"16:12:07.772","dependents":[284],"id":16,"thread":"build-5"},{"duration":0,"stepId":"io.quarkus.deployment.steps.NativeImageResourcesStep#registerPackageResources","started":"16:12:07.772","dependents":[228],"id":20,"thread":"build-7"},{"duration":0,"stepId":"io.quarkus.deployment.JniProcessor#setupJni","started":"16:12:07.802","dependents":[200],"id":199,"thread":"build-28"},{"duration":0,"stepId":"io.quarkus.jsonb.deployment.JsonbProcessor#generateCustomizer","started":"16:12:07.773","dependents":[214],"id":43,"thread":"build-9"},{"duration":0,"stepId":"io.quarkus.arc.deployment.devconsole.ArcDevConsoleProcessor#monitor","started":"16:12:07.788","dependents":[214,238,306],"id":142,"thread":"build-9"},{"duration":0,"stepId":"io.quarkus.undertow.deployment.UndertowStaticResourcesBuildStep#scanStaticResources","started":"16:12:07.796","dependents":[173],"id":171,"thread":"build-24"},{"duration":0,"stepId":"io.quarkus.qute.deployment.QuteProcessor#collectCheckedTemplates","started":"16:12:07.834","dependents":[261,259,231,263,293],"id":230,"thread":"build-31"},{"duration":0,"stepId":"io.quarkus.deployment.steps.ConfigGenerationBuildStep#runtimeDefaultsConfig","started":"16:12:07.887","dependents":[284,309],"id":283,"thread":"build-19"},{"duration":0,"stepId":"io.quarkus.arc.deployment.SyntheticBeansProcessor#initStatic","started":"16:12:07.877","dependents":[271,310],"id":268,"thread":"build-12"},{"duration":0,"stepId":"io.quarkus.deployment.console.ConsoleProcessor#setupConsole","started":"16:12:07.789","dependents":[244,242,152],"id":151,"thread":"build-21"},{"duration":0,"stepId":"io.quarkus.deployment.console.ConsoleProcessor#installCliCommands","started":"16:12:07.803","dependents":[307,306],"id":204,"thread":"build-20"},{"duration":0,"stepId":"io.quarkus.vertx.core.deployment.VertxCoreProcessor#cleanupVertxWarnings","started":"16:12:07.775","dependents":[137,253],"id":65,"thread":"build-2"},{"duration":0,"stepId":"io.quarkus.resteasy.common.deployment.ResteasyCommonProcessor#addStaticInitConfigSourceProvider","started":"16:12:07.789","dependents":[284,309],"id":147,"thread":"build-9"},{"duration":0,"stepId":"io.quarkus.arc.deployment.UnremovableAnnotationsProcessor#unremovableBeans","started":"16:12:07.774","dependents":[273,279],"id":52,"thread":"build-9"},{"duration":0,"stepId":"io.quarkus.arc.deployment.ArcProcessor#loggerProducer","started":"16:12:07.774","dependents":[214,238],"id":59,"thread":"build-9"},{"duration":0,"stepId":"io.quarkus.resteasy.deployment.ResteasyServletProcessor#webXmlMapping","started":"16:12:07.773","dependents":[233],"id":28,"thread":"build-2"},{"duration":0,"stepId":"io.quarkus.resteasy.server.common.deployment.ResteasyServerCommonProcessor#beanDefiningAnnotations","started":"16:12:07.774","dependents":[214,238,142],"id":51,"thread":"build-7"},{"duration":0,"stepId":"io.quarkus.qute.deployment.QuteProcessor#collectTemplateExtensionMethods","started":"16:12:07.833","dependents":[261,266,263],"id":229,"thread":"build-20"},{"duration":0,"stepId":"io.quarkus.arc.deployment.ConfigBuildStep#additionalBeans","started":"16:12:07.777","dependents":[214,238],"id":72,"thread":"build-10"},{"duration":0,"stepId":"io.quarkus.resteasy.common.deployment.ResteasyCommonProcessor#configInjectionStaticInitProvider","started":"16:12:07.791","dependents":[278],"id":155,"thread":"build-20"},{"duration":0,"stepId":"io.quarkus.resteasy.deployment.ResteasyBuiltinsProcessor#vertxProviders","started":"16:12:07.778","dependents":[232],"id":94,"thread":"build-2"},{"duration":0,"stepId":"io.quarkus.vertx.http.deployment.devmode.tests.TestsProcessor#runFailedTests","started":"16:12:07.803","dependents":[288,305],"id":201,"thread":"build-30"},{"duration":0,"stepId":"io.quarkus.deployment.steps.ConfigGenerationBuildStep#setupConfigOverride","started":"16:12:07.778","dependents":[],"id":92,"thread":"build-2"},{"duration":0,"stepId":"io.quarkus.jsonb.deployment.JsonbProcessor#build","started":"16:12:07.797","dependents":[214,309,238],"id":189,"thread":"build-5"},{"duration":0,"stepId":"io.quarkus.qute.deployment.QuteProcessor#collectTemplateVariants","started":"16:12:07.833","dependents":[267,231],"id":226,"thread":"build-31"},{"duration":0,"stepId":"io.quarkus.jsonp.deployment.JsonpProcessor#build","started":"16:12:07.772","dependents":[309,310],"id":11,"thread":"build-2"},{"duration":0,"stepId":"io.quarkus.deployment.console.ConsoleProcessor#setupExceptionHandler","started":"16:12:07.852","dependents":[244],"id":242,"thread":"build-31"},{"duration":0,"stepId":"io.quarkus.deployment.steps.ProfileBuildStep#defaultProfile","started":"16:12:07.786","dependents":[283],"id":138,"thread":"build-13"},{"duration":0,"stepId":"io.quarkus.netty.deployment.NettyProcessor#registerQualifiers","started":"16:12:07.772","dependents":[214,238],"id":22,"thread":"build-2"},{"duration":0,"stepId":"io.quarkus.deployment.CollectionClassProcessor#setupCollectionClasses","started":"16:12:07.778","dependents":[309],"id":88,"thread":"build-2"},{"duration":0,"stepId":"io.quarkus.deployment.steps.NativeImageFeatureStep#generateNativeResourcesList","started":"16:12:07.834","dependents":[],"id":228,"thread":"build-3"},{"duration":0,"stepId":"io.quarkus.deployment.steps.CurateOutcomeBuildStep#removeResources","started":"16:12:07.786","dependents":[293],"id":134,"thread":"build-8"},{"duration":0,"stepId":"io.quarkus.arc.deployment.ConfigBuildStep#validateConfigMappingsInjectionPoints","started":"16:12:07.887","dependents":[284,282,281],"id":279,"thread":"build-4"},{"duration":0,"stepId":"io.quarkus.arc.deployment.ConfigBuildStep#registerConfigMappingConverters","started":"16:12:07.796","dependents":[309],"id":170,"thread":"build-2"},{"duration":0,"stepId":"io.quarkus.arc.deployment.ConfigBuildStep#vetoMPConfigProperties","started":"16:12:07.772","dependents":[238],"id":10,"thread":"build-2"},{"duration":0,"stepId":"io.quarkus.qute.deployment.MessageBundleProcessor#beans","started":"16:12:07.775","dependents":[214,238],"id":66,"thread":"build-10"},{"duration":0,"stepId":"io.quarkus.deployment.steps.MainClassBuildStep#applicationReflection","started":"16:12:07.779","dependents":[309],"id":101,"thread":"build-9"},{"duration":0,"stepId":"io.quarkus.arc.deployment.TestsAsBeansProcessor#testAnnotations","started":"16:12:07.780","dependents":[214,238,142],"id":110,"thread":"build-5"},{"duration":0,"stepId":"io.quarkus.smallrye.context.deployment.SmallRyeContextPropagationProcessor#registerBean","started":"16:12:07.779","dependents":[214,238],"id":104,"thread":"build-9"},{"duration":0,"stepId":"io.quarkus.arc.deployment.ConfigBuildStep#registerConfigClasses","started":"16:12:07.887","dependents":[310],"id":281,"thread":"build-22"},{"duration":0,"stepId":"io.quarkus.vertx.http.deployment.devmode.tests.TestsProcessor#results","started":"16:12:07.772","dependents":[287],"id":8,"thread":"build-3"},{"duration":0,"stepId":"io.quarkus.arc.deployment.HotDeploymentConfigBuildStep#startup","started":"16:12:07.778","dependents":[108],"id":93,"thread":"build-2"},{"duration":0,"stepId":"io.quarkus.qute.deployment.devconsole.QuteDevConsoleProcessor#invokeEndpoint","started":"16:12:07.780","dependents":[288,305,310],"id":116,"thread":"build-9"},{"duration":0,"stepId":"io.quarkus.deployment.ide.IdeProcessor#effectiveIde","started":"16:12:07.852","dependents":[243,244,305,242],"id":241,"thread":"build-22"},{"duration":0,"stepId":"io.quarkus.deployment.steps.AdditionalClassLoaderResourcesBuildStep#appendAdditionalClassloaderResources","started":"16:12:07.772","dependents":[169],"id":14,"thread":"build-7"},{"duration":0,"stepId":"io.quarkus.deployment.steps.BootstrapConfigSetupBuildStep#setupBootstrapConfig","started":"16:12:07.777","dependents":[158,310],"id":75,"thread":"build-10"},{"duration":0,"stepId":"io.quarkus.arc.deployment.ReflectiveBeanClassesProcessor#implicitReflectiveBeanClasses","started":"16:12:07.857","dependents":[289],"id":250,"thread":"build-29"},{"duration":0,"stepId":"io.quarkus.arc.deployment.staticmethods.InterceptedStaticMethodsProcessor#callInitializer","started":"16:12:07.924","dependents":[310],"id":291,"thread":"build-37"},{"duration":0,"stepId":"io.quarkus.qute.deployment.QuteProcessor#excludeTypeChecks","started":"16:12:07.781","dependents":[261,263],"id":117,"thread":"build-3"},{"duration":0,"stepId":"io.quarkus.vertx.deployment.VertxProcessor#collectEventConsumers","started":"16:12:07.857","dependents":[271,254],"id":251,"thread":"build-32"},{"duration":0,"stepId":"io.quarkus.resteasy.deployment.ResteasyBuiltinsProcessor#addReactiveRoutesExceptionMapper","started":"16:12:07.781","dependents":[310],"id":118,"thread":"build-11"},{"duration":0,"stepId":"io.quarkus.deployment.logging.LoggingResourceProcessor#setupLoggingStaticInit","started":"16:12:07.774","dependents":[310],"id":56,"thread":"build-6"},{"duration":0,"stepId":"io.quarkus.netty.deployment.NettyProcessor#limitArenaSize","started":"16:12:07.774","dependents":[310],"id":50,"thread":"build-9"},{"duration":0,"stepId":"io.quarkus.vertx.deployment.VertxProcessor#unremovableBeans","started":"16:12:07.777","dependents":[273,279],"id":70,"thread":"build-10"},{"duration":0,"stepId":"io.quarkus.arc.deployment.ArcProcessor#validateAsyncObserverExceptionHandlers","started":"16:12:07.887","dependents":[289],"id":276,"thread":"build-29"},{"duration":0,"stepId":"io.quarkus.qute.deployment.QuteProcessor#validateTemplateInjectionPoints","started":"16:12:07.887","dependents":[289],"id":280,"thread":"build-3"},{"duration":0,"stepId":"io.quarkus.vertx.http.deployment.HttpSecurityProcessor#builtins","started":"16:12:07.778","dependents":[214,148,238],"id":80,"thread":"build-6"},{"duration":0,"stepId":"io.quarkus.deployment.console.ConsoleProcessor#helpCommand","started":"16:12:07.778","dependents":[204],"id":89,"thread":"build-10"},{"duration":0,"stepId":"io.quarkus.deployment.index.ApplicationArchiveBuildStep#addConfiguredIndexedDependencies","started":"16:12:07.783","dependents":[165],"id":125,"thread":"build-15"},{"duration":0,"stepId":"io.quarkus.arc.deployment.TestsAsBeansProcessor#testClassBeans","started":"16:12:07.778","dependents":[214,238],"id":98,"thread":"build-2"},{"duration":0,"stepId":"io.quarkus.deployment.logging.LoggingResourceProcessor#setMinLevelForInitialConfigurator","started":"16:12:07.798","dependents":[310],"id":193,"thread":"build-26"},{"duration":0,"stepId":"io.quarkus.deployment.steps.ConfigGenerationBuildStep#builderMappings","started":"16:12:07.887","dependents":[284,309],"id":282,"thread":"build-16"},{"duration":0,"stepId":"io.quarkus.deployment.dev.IsolatedDevModeMain$5$1@1c08ea71","started":"16:12:07.773","dependents":[238],"id":35,"thread":"build-5"},{"duration":0,"stepId":"io.quarkus.arc.deployment.ArcProcessor#quarkusApplication","started":"16:12:07.796","dependents":[214,238],"id":180,"thread":"build-11"},{"duration":0,"stepId":"io.quarkus.vertx.http.deployment.devmode.console.DevConsoleProcessor#setupWebJar","started":"16:12:07.771","dependents":[236],"id":3,"thread":"build-1"},{"duration":0,"stepId":"io.quarkus.vertx.http.deployment.VertxHttpProcessor#httpRoot","started":"16:12:07.781","dependents":[303,119,301,298,234,118,120],"id":114,"thread":"build-6"},{"duration":0,"stepId":"io.quarkus.qute.deployment.devconsole.QuteDevConsoleProcessor#collectTemplateInfo","started":"16:12:07.834","dependents":[287],"id":231,"thread":"build-20"},{"duration":0,"stepId":"io.quarkus.arc.deployment.ConfigBuildStep#registerConfigRootsAsBeans","started":"16:12:07.779","dependents":[268,270,269],"id":103,"thread":"build-11"},{"duration":0,"stepId":"io.quarkus.deployment.steps.PreloadClassesBuildStep#registerPreInitClasses","started":"16:12:07.772","dependents":[],"id":13,"thread":"build-6"},{"duration":0,"stepId":"io.quarkus.smallrye.context.deployment.SmallRyeContextPropagationProcessor#createSynthBeansForConfiguredInjectionPoints","started":"16:12:07.857","dependents":[268,270,269,310],"id":249,"thread":"build-19"},{"duration":0,"stepId":"io.quarkus.arc.deployment.ArcProcessor#marker","started":"16:12:07.772","dependents":[165],"id":24,"thread":"build-9"},{"duration":0,"stepId":"io.quarkus.qute.deployment.QuteProcessor#registerLocatorsAsSingleton","started":"16:12:07.773","dependents":[214,238,142],"id":41,"thread":"build-10"},{"duration":0,"stepId":"io.quarkus.deployment.ExtensionLoader#config","started":"16:12:07.774","dependents":[221,49,195,50,51,175,163,263,53,214,186,259,165,56,162,299,205,279,134,161,155,232,190,80,106,142,159,99,303,103,284,191,289,295,238,151,298,196,308,156,160,147,224,236,164,188,114,293,275,181,117,193,178,288,166,168,185,266,152,133,282,199,302,252,310,209,294,255,210,261,233,285,128,122,124,283,125,253,307,126,148,219,227,241,304,127,149,129,130,131],"id":46,"thread":"build-8"},{"duration":0,"stepId":"io.quarkus.arc.deployment.ArcProcessor#quarkusMain","started":"16:12:07.772","dependents":[214,238,142],"id":9,"thread":"build-1"},{"duration":0,"stepId":"io.quarkus.deployment.logging.LoggingResourceProcessor#setProperty","started":"16:12:07.778","dependents":[310],"id":90,"thread":"build-10"},{"duration":0,"stepId":"io.quarkus.vertx.http.deployment.devmode.BuildMetricsDevConsoleProcessor#collectMetrics","started":"16:12:07.772","dependents":[287],"id":12,"thread":"build-1"},{"duration":0,"stepId":"io.quarkus.smallrye.context.deployment.SmallRyeContextPropagationProcessor#transformInjectionPoint","started":"16:12:07.789","dependents":[238],"id":150,"thread":"build-17"},{"duration":0,"stepId":"io.quarkus.undertow.deployment.UndertowStaticResourcesBuildStep#handleGeneratedWebResources","started":"16:12:07.789","dependents":[],"id":146,"thread":"build-10"},{"duration":0,"stepId":"io.quarkus.qute.deployment.QuteProcessor#feature","started":"16:12:07.779","dependents":[310],"id":100,"thread":"build-9"},{"duration":0,"stepId":"io.quarkus.resteasy.common.deployment.ResteasyCommonProcessor#disableDefaultExceptionMapper","started":"16:12:07.774","dependents":[310],"id":49,"thread":"build-5"},{"duration":0,"stepId":"io.quarkus.resteasy.qute.deployment.ResteasyQuteProcessor#feature","started":"16:12:07.805","dependents":[310],"id":208,"thread":"build-12"},{"duration":0,"stepId":"io.quarkus.deployment.steps.RegisterForReflectionBuildStep#build","started":"16:12:07.806","dependents":[309,239],"id":211,"thread":"build-32"},{"duration":0,"stepId":"io.quarkus.arc.deployment.AutoInjectFieldProcessor#autoInjectQualifiers","started":"16:12:07.833","dependents":[221,223,233],"id":218,"thread":"build-15"},{"duration":0,"stepId":"io.quarkus.vertx.deployment.VertxProcessor#autoAddScope","started":"16:12:07.772","dependents":[223],"id":17,"thread":"build-6"},{"duration":0,"stepId":"io.quarkus.vertx.http.deployment.VertxHttpProcessor#hostDefault","started":"16:12:07.774","dependents":[153],"id":47,"thread":"build-10"},{"duration":0,"stepId":"io.quarkus.deployment.steps.BannerProcessor#watchBannerChanges","started":"16:12:07.783","dependents":[265],"id":127,"thread":"build-15"},{"duration":0,"stepId":"io.quarkus.vertx.http.deployment.devmode.console.DevConsoleProcessor#setupDevConsoleRoutes_8bb86a3e770caadb970f4facb490e30df7a2a187","started":"16:12:07.842","dependents":[305,300,302,310],"id":237,"thread":"build-20"},{"duration":0,"stepId":"io.quarkus.vertx.http.deployment.VertxHttpProcessor#additionalBeans","started":"16:12:07.773","dependents":[214,238],"id":26,"thread":"build-1"},{"duration":0,"stepId":"io.quarkus.arc.deployment.ArcProcessor#exposeCustomScopeNames","started":"16:12:07.779","dependents":[214,219,223,233,191,238,142,252,113],"id":107,"thread":"build-3"},{"duration":0,"stepId":"io.quarkus.deployment.logging.LoggingResourceProcessor#setUpDarkeningDefault","started":"16:12:07.779","dependents":[283],"id":105,"thread":"build-11"},{"duration":0,"stepId":"io.quarkus.deployment.steps.CombinedIndexBuildStep#build","started":"16:12:07.796","dependents":[170,174,235,172,246,175,176,247,177,178,179,180,299,182,183,233,184,232,211,187,189,190,239,253,278,191,220,194,238],"id":169,"thread":"build-14"},{"duration":0,"stepId":"io.quarkus.resteasy.server.common.deployment.ResteasyServerCommonProcessor#processPathInterfaceImplementors","started":"16:12:07.797","dependents":[273,214,238,279],"id":191,"thread":"build-17"},{"duration":0,"stepId":"io.quarkus.arc.deployment.ArcProcessor#registerSyntheticObservers","started":"16:12:07.880","dependents":[273,309,289,272,279],"id":271,"thread":"build-31"},{"duration":0,"stepId":"io.quarkus.deployment.steps.ShutdownListenerBuildStep#setupShutdown","started":"16:12:07.931","dependents":[310],"id":304,"thread":"build-36"},{"duration":0,"stepId":"io.quarkus.vertx.deployment.EventBusCodecProcessor#registerCodecs","started":"16:12:07.833","dependents":[254,309],"id":220,"thread":"build-29"},{"duration":0,"stepId":"io.quarkus.arc.deployment.BuildTimeEnabledProcessor#ifBuildProfile","started":"16:12:07.796","dependents":[192,233],"id":174,"thread":"build-18"},{"duration":0,"stepId":"io.quarkus.deployment.steps.DevModeBuildStep#watchChanges","started":"16:12:07.782","dependents":[265],"id":122,"thread":"build-7"},{"duration":0,"stepId":"io.quarkus.deployment.dev.testing.TestTracingProcessor#handle","started":"16:12:07.774","dependents":[137,253],"id":62,"thread":"build-9"},{"duration":0,"stepId":"io.quarkus.arc.deployment.WrongAnnotationUsageProcessor#detect","started":"16:12:07.857","dependents":[289],"id":252,"thread":"build-12"},{"duration":0,"stepId":"io.quarkus.vertx.core.deployment.VertxCoreProcessor#build_9d6b7122fb368970c50c3a870d1f672392cd8afb","started":"16:12:07.773","dependents":[309,228,200],"id":39,"thread":"build-1"},{"duration":0,"stepId":"io.quarkus.deployment.dev.ConfigureDisableInstrumentationBuildStep#configure","started":"16:12:07.779","dependents":[307,306],"id":108,"thread":"build-6"},{"duration":0,"stepId":"io.quarkus.undertow.deployment.UndertowStaticResourcesBuildStep#nativeImageResources","started":"16:12:07.796","dependents":[228],"id":173,"thread":"build-2"},{"duration":0,"stepId":"io.quarkus.deployment.logging.LoggingWithPanacheProcessor#process","started":"16:12:07.796","dependents":[293],"id":176,"thread":"build-10"},{"duration":0,"stepId":"io.quarkus.arc.deployment.ConfigBuildStep#registerCustomConfigBeanTypes","started":"16:12:07.857","dependents":[268,309,270,269],"id":248,"thread":"build-3"},{"duration":0,"stepId":"io.quarkus.vertx.http.deployment.devmode.console.DevConsoleProcessor#setupDevConsoleWebjar","started":"16:12:07.772","dependents":[236],"id":15,"thread":"build-3"},{"duration":0,"stepId":"io.quarkus.arc.deployment.BuildTimeEnabledProcessor#conditionTransformer","started":"16:12:07.797","dependents":[238],"id":192,"thread":"build-14"},{"duration":0,"stepId":"io.quarkus.vertx.http.deployment.HttpSecurityProcessor#setupAuthenticationMechanisms","started":"16:12:07.789","dependents":[303,214,289,238,310],"id":148,"thread":"build-14"},{"duration":0,"stepId":"io.quarkus.vertx.http.deployment.devmode.console.DevConsoleProcessor#config","started":"16:12:07.773","dependents":[287],"id":44,"thread":"build-5"},{"duration":0,"stepId":"io.quarkus.deployment.steps.CurateOutcomeBuildStep#curateOutcome","started":"16:12:07.786","dependents":[134,161,305,139,140,224,236,142,287,293,203,288,143,165],"id":133,"thread":"build-27"},{"duration":0,"stepId":"io.quarkus.deployment.dev.testing.TestTracingProcessor#sharedStateListener","started":"16:12:07.773","dependents":[152],"id":27,"thread":"build-9"},{"duration":0,"stepId":"io.quarkus.resteasy.jsonb.deployment.ResteasyJsonbProcessor#feature","started":"16:12:07.772","dependents":[310],"id":25,"thread":"build-2"},{"duration":0,"stepId":"io.quarkus.vertx.http.deployment.devmode.console.DevConsoleProcessor#runtimeTemplates","started":"16:12:07.947","dependents":[310],"id":306,"thread":"build-26"},{"duration":0,"stepId":"io.quarkus.resteasy.server.common.deployment.ResteasyLogFilterBuildStep#setupLogFilters","started":"16:12:07.778","dependents":[137,253],"id":86,"thread":"build-2"},{"duration":0,"stepId":"io.quarkus.vertx.core.deployment.VertxCoreProcessor#doNotRemoveVertxOptionsCustomizers","started":"16:12:07.777","dependents":[273,279],"id":73,"thread":"build-10"},{"duration":0,"stepId":"io.quarkus.arc.deployment.ConfigBuildStep#registerConfigMappingsBean","started":"16:12:07.857","dependents":[271],"id":246,"thread":"build-4"},{"duration":0,"stepId":"io.quarkus.deployment.steps.NativeImageConfigBuildStep#build","started":"16:12:07.802","dependents":[310],"id":200,"thread":"build-11"},{"duration":0,"stepId":"io.quarkus.deployment.steps.ConfigGenerationBuildStep#extensionMappings","started":"16:12:07.796","dependents":[275,309,246,247,278,279],"id":175,"thread":"build-23"},{"duration":0,"stepId":"io.quarkus.qute.deployment.QuteProcessor#collectTemplateDataAnnotations","started":"16:12:07.833","dependents":[261,266,222,263],"id":217,"thread":"build-3"},{"duration":0,"stepId":"io.quarkus.resteasy.deployment.RestPathAnnotationProcessor#findRestPaths","started":"16:12:07.842","dependents":[238],"id":235,"thread":"build-20"},{"duration":0,"stepId":"io.quarkus.arc.deployment.ConfigBuildStep#validateConfigInjectionPoints","started":"16:12:07.887","dependents":[292],"id":274,"thread":"build-12"},{"duration":0,"stepId":"io.quarkus.deployment.logging.LoggingResourceProcessor#registerMetrics","started":"16:12:07.797","dependents":[253,310],"id":188,"thread":"build-25"},{"duration":0,"stepId":"io.quarkus.qute.deployment.MessageBundleProcessor#validateMessageBundleMethods","started":"16:12:07.861","dependents":[264],"id":260,"thread":"build-22"},{"duration":0,"stepId":"io.quarkus.arc.deployment.devconsole.ArcDevConsoleProcessor#exposeArcContainer","started":"16:12:07.786","dependents":[306,310],"id":139,"thread":"build-9"},{"duration":0,"stepId":"io.quarkus.vertx.http.deployment.devmode.tests.TestsProcessor#toggleInstrumentation","started":"16:12:07.778","dependents":[288,305],"id":83,"thread":"build-10"},{"duration":0,"stepId":"io.quarkus.vertx.core.deployment.VertxCoreProcessor#preventLoggerContention","started":"16:12:07.778","dependents":[84],"id":82,"thread":"build-6"},{"duration":0,"stepId":"io.quarkus.deployment.ForkJoinPoolProcessor#setProperty","started":"16:12:07.777","dependents":[310],"id":74,"thread":"build-10"},{"duration":0,"stepId":"io.quarkus.vertx.http.deployment.devmode.tests.TestsProcessor#handleTestResult","started":"16:12:07.773","dependents":[288,305],"id":32,"thread":"build-9"},{"duration":0,"stepId":"io.quarkus.mutiny.deployment.MutinyProcessor#runtimeInit","started":"16:12:07.800","dependents":[310],"id":197,"thread":"build-26"},{"duration":0,"stepId":"io.quarkus.resteasy.deployment.ResteasyServletProcessor#addServletsToExceptionMapper","started":"16:12:07.927","dependents":[310],"id":297,"thread":"build-26"},{"duration":0,"stepId":"io.quarkus.qute.deployment.QuteProcessor#validateTemplateDataNamespaces","started":"16:12:07.833","dependents":[307,306],"id":222,"thread":"build-32"},{"duration":0,"stepId":"io.quarkus.arc.deployment.StartupBuildSteps#registerStartupObservers","started":"16:12:07.881","dependents":[273],"id":272,"thread":"build-22"},{"duration":0,"stepId":"io.quarkus.deployment.pkg.steps.JarResultBuildStep#outputTarget","started":"16:12:07.791","dependents":[157],"id":156,"thread":"build-22"},{"duration":0,"stepId":"io.quarkus.netty.deployment.NettyProcessor#setNettyMachineId","started":"16:12:07.771","dependents":[310],"id":4,"thread":"build-3"},{"duration":0,"stepId":"io.quarkus.vertx.http.deployment.devmode.tests.TestsProcessor#toggleTestOutput","started":"16:12:07.774","dependents":[288,305],"id":58,"thread":"build-9"},{"duration":0,"stepId":"io.quarkus.vertx.http.deployment.devmode.tests.TestsProcessor#runAllTests","started":"16:12:07.772","dependents":[288,305],"id":7,"thread":"build-5"},{"duration":0,"stepId":"io.quarkus.arc.deployment.ArcProcessor#launchMode","started":"16:12:07.778","dependents":[214,238],"id":85,"thread":"build-10"},{"duration":0,"stepId":"io.quarkus.arc.deployment.ObserverValidationProcessor#validateApplicationObserver","started":"16:12:07.887","dependents":[289],"id":277,"thread":"build-19"},{"duration":0,"stepId":"io.quarkus.deployment.steps.CapabilityAggregationStep#aggregateCapabilities","started":"16:12:07.788","dependents":[235,232,211,190,147,144,213,148,171,173,238,145,146,298,149,296],"id":143,"thread":"build-13"},{"duration":0,"stepId":"io.quarkus.arc.deployment.LoggingBeanSupportProcessor#discoveredComponents","started":"16:12:07.783","dependents":[214,238,142],"id":123,"thread":"build-15"},{"duration":0,"stepId":"io.quarkus.arc.deployment.ConfigBuildStep#validateConfigPropertiesInjectionPoints","started":"16:12:07.887","dependents":[281],"id":275,"thread":"build-22"},{"duration":0,"stepId":"io.quarkus.resteasy.qute.deployment.ResteasyQuteProcessor#registerProviders","started":"16:12:07.773","dependents":[232],"id":37,"thread":"build-2"},{"duration":0,"stepId":"io.quarkus.deployment.dev.io.NioThreadPoolDevModeProcessor#setupTCCL","started":"16:12:07.780","dependents":[310],"id":115,"thread":"build-11"},{"duration":0,"stepId":"io.quarkus.arc.deployment.ArcProcessor#transformListAllInjectionPoints","started":"16:12:07.773","dependents":[238],"id":31,"thread":"build-2"},{"duration":0,"stepId":"io.quarkus.vertx.deployment.VertxProcessor#featureAndCapability","started":"16:12:07.778","dependents":[143,310],"id":87,"thread":"build-10"},{"duration":0,"stepId":"io.quarkus.arc.deployment.ConfigBuildStep#warnStaticInitInjectionPoints","started":"16:12:07.887","dependents":[283],"id":278,"thread":"build-16"},{"duration":0,"stepId":"io.quarkus.qute.deployment.QuteProcessor#validateCheckedFragments","started":"16:12:07.862","dependents":[289],"id":262,"thread":"build-22"},{"duration":0,"stepId":"io.quarkus.deployment.logging.LoggingResourceProcessor#setupStackTraceFormatter","started":"16:12:07.853","dependents":[253],"id":244,"thread":"build-22"},{"duration":0,"stepId":"io.quarkus.qute.deployment.QuteProcessor#processTemplateErrors","started":"16:12:07.862","dependents":[307,306],"id":264,"thread":"build-22"},{"duration":0,"stepId":"io.quarkus.arc.deployment.SyntheticBeansProcessor#initRegular","started":"16:12:07.877","dependents":[271],"id":269,"thread":"build-31"},{"duration":0,"stepId":"io.quarkus.arc.deployment.HotDeploymentConfigBuildStep#configFile","started":"16:12:07.772","dependents":[265],"id":5,"thread":"build-1"},{"duration":0,"stepId":"io.quarkus.arc.deployment.BuildTimeEnabledProcessor#unlessBuildProfile","started":"16:12:07.797","dependents":[192,233],"id":184,"thread":"build-5"},{"duration":0,"stepId":"io.quarkus.deployment.pkg.steps.PackageTypeVerificationBuildStep#verify","started":"16:12:07.805","dependents":[307,306],"id":210,"thread":"build-31"},{"duration":0,"stepId":"io.quarkus.deployment.console.ConsoleProcessor#quitCommand","started":"16:12:07.773","dependents":[204],"id":40,"thread":"build-2"},{"duration":0,"stepId":"io.quarkus.arc.deployment.ConfigBuildStep#validateConfigValues","started":"16:12:07.926","dependents":[309,310],"id":292,"thread":"build-27"},{"duration":0,"stepId":"io.quarkus.qute.deployment.MessageBundleProcessor#validateMessageBundleMethodsInTemplates","started":"16:12:07.862","dependents":[264,266],"id":263,"thread":"build-31"},{"duration":0,"stepId":"io.quarkus.deployment.steps.ConfigGenerationBuildStep#generateConfigClass","started":"16:12:07.888","dependents":[309],"id":284,"thread":"build-16"},{"duration":0,"stepId":"io.quarkus.deployment.logging.LoggingResourceProcessor#setupLogFilters","started":"16:12:07.772","dependents":[137,253],"id":19,"thread":"build-3"},{"duration":0,"stepId":"io.quarkus.arc.deployment.AutoProducerMethodsProcessor#annotationTransformer","started":"16:12:07.833","dependents":[238],"id":219,"thread":"build-12"},{"duration":0,"stepId":"io.quarkus.deployment.recording.substitutions.AdditionalSubstitutionsBuildStep#additionalSubstitutions","started":"16:12:07.774","dependents":[310],"id":61,"thread":"build-9"},{"duration":0,"stepId":"io.quarkus.qute.deployment.QuteProcessor#collectTemplateGlobals","started":"16:12:07.833","dependents":[259,266,262,260],"id":216,"thread":"build-32"},{"duration":0,"stepId":"io.quarkus.vertx.http.deployment.VertxHttpProcessor#notFoundRoutes","started":"16:12:07.929","dependents":[301],"id":300,"thread":"build-15"},{"duration":0,"stepId":"io.quarkus.vertx.http.deployment.HttpSecurityProcessor#initMtlsClientAuth","started":"16:12:07.792","dependents":[268,270,269,310],"id":159,"thread":"build-18"},{"duration":0,"stepId":"io.quarkus.deployment.steps.RuntimeConfigSetupBuildStep#setupRuntimeConfig","started":"16:12:07.792","dependents":[195,163,159,307,253,164,303,181,166,295,168,304,162,299,196,308,302,209,205,310],"id":158,"thread":"build-24"},{"duration":0,"stepId":"io.quarkus.netty.deployment.NettyProcessor#cleanupUnsafeLog","started":"16:12:07.786","dependents":[137,253],"id":135,"thread":"build-14"},{"duration":0,"stepId":"io.quarkus.deployment.SslProcessor#setupNativeSsl","started":"16:12:07.783","dependents":[200],"id":124,"thread":"build-15"},{"duration":0,"stepId":"io.quarkus.deployment.steps.CapabilityAggregationStep#provideCapabilities","started":"16:12:07.788","dependents":[143],"id":140,"thread":"build-9"},{"duration":0,"stepId":"io.quarkus.vertx.http.deployment.VertxHttpProcessor#frameworkRoot","started":"16:12:07.778","dependents":[303,288,285,112,305,302,120,237],"id":99,"thread":"build-5"},{"duration":0,"stepId":"io.quarkus.qute.deployment.QuteProcessor#validateAndCollectCustomTemplateLocatorLocations","started":"16:12:07.833","dependents":[230,289,280],"id":225,"thread":"build-14"},{"duration":0,"stepId":"io.quarkus.arc.deployment.ArcProcessor#registerContextPropagation","started":"16:12:07.783","dependents":[132],"id":126,"thread":"build-15"},{"duration":0,"stepId":"io.quarkus.resteasy.deployment.ResteasyStandaloneBuildStep#staticInit","started":"16:12:07.927","dependents":[299,310],"id":298,"thread":"build-35"},{"duration":0,"stepId":"io.quarkus.deployment.steps.ConfigBuildSteps#generateConfigSources","started":"16:12:07.790","dependents":[],"id":153,"thread":"build-19"},{"duration":0,"stepId":"io.quarkus.arc.deployment.BuildTimeEnabledProcessor#ifBuildProperty","started":"16:12:07.797","dependents":[192,233],"id":182,"thread":"build-3"},{"duration":0,"stepId":"io.quarkus.arc.deployment.ArcProcessor#feature","started":"16:12:07.778","dependents":[310],"id":97,"thread":"build-2"},{"duration":0,"stepId":"io.quarkus.vertx.http.deployment.devmode.tests.TestsProcessor#forceRestart","started":"16:12:07.775","dependents":[288,305],"id":67,"thread":"build-10"},{"duration":0,"stepId":"io.quarkus.jsonb.deployment.JsonbProcessor#processJsonbAdapters","started":"16:12:07.773","dependents":[273,223,279],"id":29,"thread":"build-3"},{"duration":0,"stepId":"io.quarkus.deployment.recording.AnnotationProxyBuildStep#build","started":"16:12:07.795","dependents":[254],"id":167,"thread":"build-18"},{"duration":0,"stepId":"io.quarkus.vertx.core.deployment.VertxCoreProcessor#registerVerticleClasses","started":"16:12:07.796","dependents":[309],"id":179,"thread":"build-13"},{"duration":0,"stepId":"io.quarkus.arc.deployment.ArcProcessor#unremovableAsyncObserverExceptionHandlers","started":"16:12:07.778","dependents":[273,279],"id":95,"thread":"build-2"},{"duration":0,"stepId":"io.quarkus.deployment.steps.PreloadClassesBuildStep#preInit","started":"16:12:07.775","dependents":[310],"id":68,"thread":"build-10"},{"duration":0,"stepId":"io.quarkus.arc.deployment.LookupConditionsProcessor#suppressConditionsGenerators","started":"16:12:07.833","dependents":[238],"id":215,"thread":"build-31"},{"duration":0,"stepId":"io.quarkus.qute.deployment.QuteProcessor#validateExpressions","started":"16:12:07.861","dependents":[264,266,262,263],"id":261,"thread":"build-12"},{"duration":0,"stepId":"io.quarkus.resteasy.deployment.ResteasyBuiltinsProcessor#setupExceptionMapper","started":"16:12:07.781","dependents":[232,310],"id":119,"thread":"build-7"},{"duration":0,"stepId":"io.quarkus.deployment.pkg.steps.FileSystemResourcesBuildStep#notNormalMode","started":"16:12:07.791","dependents":[],"id":157,"thread":"build-20"},{"duration":0,"stepId":"io.quarkus.resteasy.deployment.ResteasyBuiltinsProcessor#addAdditionalEndpointsExceptionMapper","started":"16:12:07.929","dependents":[310],"id":301,"thread":"build-26"},{"duration":0,"stepId":"io.quarkus.vertx.http.deployment.devmode.console.ConfigEditorProcessor#handleRequests","started":"16:12:07.773","dependents":[288,305],"id":45,"thread":"build-10"},{"duration":0,"stepId":"io.quarkus.vertx.http.deployment.VertxHttpProcessor#filterMultipleVertxInstancesWarning","started":"16:12:07.777","dependents":[137,253],"id":71,"thread":"build-10"},{"duration":0,"stepId":"io.quarkus.resteasy.deployment.ResteasyServletProcessor#build","started":"16:12:07.927","dependents":[309,297,310],"id":296,"thread":"build-15"},{"duration":0,"stepId":"io.quarkus.arc.deployment.StartupBuildSteps#addScope","started":"16:12:07.781","dependents":[223],"id":113,"thread":"build-7"},{"duration":0,"stepId":"io.quarkus.deployment.logging.LoggingResourceProcessor#setUpDefaultLogCleanupFilters","started":"16:12:07.786","dependents":[283],"id":137,"thread":"build-8"},{"duration":0,"stepId":"io.quarkus.resteasy.deployment.ResteasyServletProcessor#jaxrsConfig","started":"16:12:07.842","dependents":[235],"id":234,"thread":"build-31"},{"duration":0,"stepId":"io.quarkus.deployment.steps.MainClassBuildStep#mainClassBuildStep","started":"16:12:07.796","dependents":[],"id":178,"thread":"build-8"},{"duration":0,"stepId":"io.quarkus.mutiny.deployment.MutinyProcessor#buildTimeInit","started":"16:12:07.779","dependents":[310],"id":102,"thread":"build-9"},{"duration":0,"stepId":"io.quarkus.arc.deployment.LifecycleEventsBuildStep#startupEvent","started":"16:12:07.947","dependents":[308,310],"id":307,"thread":"build-36"},{"duration":0,"stepId":"io.quarkus.netty.deployment.NettyProcessor#cleanupMacDNSInLog","started":"16:12:07.773","dependents":[137,253],"id":36,"thread":"build-10"},{"duration":0,"stepId":"io.quarkus.arc.deployment.CommandLineArgumentsProcessor#commandLineArgs","started":"16:12:07.774","dependents":[268,214,238,270,269],"id":63,"thread":"build-9"},{"duration":0,"stepId":"io.quarkus.arc.deployment.AutoAddScopeProcessor#annotationTransformer","started":"16:12:07.833","dependents":[273,238,279],"id":223,"thread":"build-31"},{"duration":0,"stepId":"io.quarkus.resteasy.common.deployment.ResteasyCommonProcessor#setupGzipProviders","started":"16:12:07.785","dependents":[232],"id":130,"thread":"build-15"},{"duration":0,"stepId":"io.quarkus.resteasy.deployment.ResteasyBuiltinsProcessor#setUpSecurity","started":"16:12:07.788","dependents":[214,232,238],"id":144,"thread":"build-8"},{"duration":0,"stepId":"io.quarkus.deployment.ConstructorPropertiesProcessor#build","started":"16:12:07.796","dependents":[309],"id":177,"thread":"build-7"},{"duration":0,"stepId":"io.quarkus.vertx.http.deployment.HttpSecurityProcessor#initFormAuth","started":"16:12:07.793","dependents":[268,305,300,270,302,269,310],"id":162,"thread":"build-14"},{"duration":0,"stepId":"io.quarkus.deployment.dev.testing.TestTracingProcessor#startTesting","started":"16:12:07.789","dependents":[253,307,306],"id":152,"thread":"build-17"},{"duration":0,"stepId":"io.quarkus.arc.deployment.StartupBuildSteps#unremovableBeans","started":"16:12:07.772","dependents":[273,279],"id":6,"thread":"build-2"},{"duration":0,"stepId":"io.quarkus.arc.deployment.ConfigBuildStep#registerConfigPropertiesBean","started":"16:12:07.857","dependents":[271],"id":247,"thread":"build-16"},{"duration":0,"stepId":"io.quarkus.resteasy.common.deployment.ResteasyCommonProcessor#registerJsonContextResolvers","started":"16:12:07.797","dependents":[273,214,232,238,279],"id":190,"thread":"build-6"},{"duration":0,"stepId":"io.quarkus.resteasy.server.common.deployment.ResteasyServerCommonProcessor#registerCompatibleAnnotationPrefixes","started":"16:12:07.774","dependents":[233],"id":53,"thread":"build-2"},{"duration":0,"stepId":"io.quarkus.vertx.core.deployment.VertxCoreProcessor#filterNettyHostsFileParsingWarn","started":"16:12:07.774","dependents":[137,253],"id":57,"thread":"build-6"},{"duration":0,"stepId":"io.quarkus.resteasy.common.deployment.ResteasyCommonProcessor#resteasyConfig","started":"16:12:07.789","dependents":[232],"id":149,"thread":"build-2"},{"duration":0,"stepId":"io.quarkus.vertx.core.deployment.VertxCoreProcessor#overrideContextInternalInterfaceToAddSafeGuards","started":"16:12:07.774","dependents":[293],"id":48,"thread":"build-11"},{"duration":0,"stepId":"io.quarkus.arc.deployment.ArcProcessor#convertLegacyAdditionalStereotypes","started":"16:12:07.771","dependents":[219,238],"id":1,"thread":"build-1"},{"duration":0,"stepId":"io.quarkus.arc.deployment.ArcProcessor#setupExecutor","started":"16:12:07.800","dependents":[310],"id":198,"thread":"build-11"},{"duration":0,"stepId":"io.quarkus.arc.deployment.ConfigBuildStep#generateConfigClasses","started":"16:12:07.796","dependents":[275,309,246,247,278,279],"id":172,"thread":"build-21"},{"duration":0,"stepId":"io.quarkus.arc.deployment.staticmethods.InterceptedStaticMethodsProcessor#processInterceptedStaticMethods","started":"16:12:07.859","dependents":[309,293],"id":257,"thread":"build-22"},{"duration":0,"stepId":"io.quarkus.qute.deployment.QuteProcessor#additionalBeans","started":"16:12:07.771","dependents":[214,238],"id":2,"thread":"build-4"},{"duration":0,"stepId":"io.quarkus.qute.deployment.QuteProcessor#collectTemplateFilePaths","started":"16:12:07.833","dependents":[230,259,280],"id":227,"thread":"build-32"},{"duration":0,"stepId":"io.quarkus.vertx.http.deployment.VertxHttpProcessor#openSocket","started":"16:12:07.948","dependents":[309,310],"id":308,"thread":"build-26"},{"duration":0,"stepId":"io.quarkus.netty.deployment.NettyProcessor#eagerlyInitClass","started":"16:12:07.778","dependents":[310],"id":96,"thread":"build-10"},{"duration":0,"stepId":"io.quarkus.arc.deployment.AutoInjectFieldProcessor#annotationTransformer","started":"16:12:07.833","dependents":[238],"id":221,"thread":"build-3"},{"duration":0,"stepId":"io.quarkus.vertx.http.deployment.devmode.tests.TestsProcessor#toggleLiveReloadEnabled","started":"16:12:07.773","dependents":[288,305],"id":33,"thread":"build-10"},{"duration":0,"stepId":"io.quarkus.deployment.steps.ApplicationInfoBuildStep#create","started":"16:12:07.785","dependents":[310],"id":131,"thread":"build-15"},{"duration":0,"stepId":"io.quarkus.vertx.deployment.VertxProcessor#registerBean","started":"16:12:07.778","dependents":[214,238],"id":91,"thread":"build-2"},{"duration":0,"stepId":"io.quarkus.deployment.ExtensionLoader#booleanSupplierFactory","started":"16:12:07.774","dependents":[140],"id":55,"thread":"build-9"},{"duration":0,"stepId":"io.quarkus.deployment.logging.LoggingResourceProcessor#setUpDefaultLevels","started":"16:12:07.778","dependents":[283,253],"id":84,"thread":"build-2"},{"duration":0,"stepId":"io.quarkus.netty.deployment.NettyProcessor#registerEventLoopBeans","started":"16:12:07.804","dependents":[268,270,269,310],"id":206,"thread":"build-20"},{"duration":0,"stepId":"io.quarkus.arc.deployment.ArcProcessor#signalBeanContainerReady","started":"16:12:07.924","dependents":[303,291,295,292,307,310,294],"id":290,"thread":"build-28"},{"duration":0,"stepId":"io.quarkus.deployment.steps.BlockingOperationControlBuildStep#blockingOP","started":"16:12:07.804","dependents":[310],"id":207,"thread":"build-29"},{"duration":0,"stepId":"io.quarkus.deployment.pkg.steps.PackageTypeVerificationBuildStep#builtins","started":"16:12:07.775","dependents":[210],"id":69,"thread":"build-10"},{"duration":0,"stepId":"io.quarkus.vertx.http.deployment.devmode.tests.TestsProcessor#printfailures","started":"16:12:07.774","dependents":[288,305],"id":60,"thread":"build-9"},{"duration":0,"stepId":"io.quarkus.vertx.http.deployment.devmode.console.DevConsoleProcessor#buildTimeTemplates","started":"16:12:07.892","dependents":[307,306],"id":287,"thread":"build-15"},{"duration":0,"stepId":"io.quarkus.resteasy.qute.deployment.ResteasyQuteProcessor#ignoreReflectiveWarning","started":"16:12:07.773","dependents":[239],"id":30,"thread":"build-2"},{"duration":0,"stepId":"io.quarkus.resteasy.deployment.RestPathAnnotationProcessor#registerBeanClasses","started":"16:12:07.789","dependents":[214,238],"id":145,"thread":"build-7"},{"duration":0,"stepId":"io.quarkus.deployment.steps.DevServicesConfigBuildStep#deprecated","started":"16:12:07.772","dependents":[42],"id":21,"thread":"build-1"},{"duration":0,"stepId":"io.quarkus.vertx.http.deployment.VertxHttpProcessor#logging","started":"16:12:07.778","dependents":[84],"id":79,"thread":"build-10"},{"duration":0,"stepId":"io.quarkus.vertx.http.deployment.devmode.tests.TestsProcessor#handleTestStatus","started":"16:12:07.778","dependents":[288,305],"id":81,"thread":"build-2"},{"duration":0,"stepId":"io.quarkus.deployment.steps.ReflectionDiagnosticProcessor#writeReflectionData","started":"16:12:07.948","dependents":[],"id":309,"thread":"build-36"},{"duration":0,"stepId":"io.quarkus.vertx.http.deployment.VertxHttpProcessor#shouldNotRemoveHttpServerOptionsCustomizers","started":"16:12:07.773","dependents":[273,279],"id":38,"thread":"build-6"}],"started":"2023-05-01T16:12:07.77","buildTarget":"projeto-final-1.0.0-SNAPSHOT"}